sighted/__init__.py
sighted/language.py
sighted/parts_of_speech.py
sighted/en_core_web_sm/LICENSES_SOURCES
sighted/en_core_web_sm/accuracy.json
sighted/en_core_web_sm/config.cfg
sighted/en_core_web_sm/meta.json
sighted/en_core_web_sm/tokenizer
sighted/en_core_web_sm/attribute_ruler/patterns
sighted/en_core_web_sm/lemmatizer/lookups/lookups.bin
sighted/en_core_web_sm/ner/cfg
sighted/en_core_web_sm/ner/model
sighted/en_core_web_sm/ner/moves
sighted/en_core_web_sm/parser/cfg
sighted/en_core_web_sm/parser/model
sighted/en_core_web_sm/parser/moves
sighted/en_core_web_sm/senter/cfg
sighted/en_core_web_sm/senter/model
sighted/en_core_web_sm/tagger/cfg
sighted/en_core_web_sm/tagger/model
sighted/en_core_web_sm/tok2vec/cfg
sighted/en_core_web_sm/tok2vec/model
sighted/en_core_web_sm/vocab/key2row
sighted/en_core_web_sm/vocab/lookups.bin
sighted/en_core_web_sm/vocab/strings.json
sighted/en_core_web_sm/vocab/vectors
sighted/en_core_web_sm/vocab/vectors.cfg
sighted/literal/__init__.py
sighted/literal/algo.py
sighted/literal/lang.py
sighted-0.0.4.dist-info/LICENSE
sighted-0.0.4.dist-info/METADATA
sighted-0.0.4.dist-info/WHEEL
sighted-0.0.4.dist-info/top_level.txt
sighted-0.0.4.dist-info/RECORD
