Metadata-Version: 2.1
Name: sighted
Version: 0.0.4
Summary: Your Brain Reads Faster Than Your Eyes
Author-email: Sadra Yahyapour <lnxpylnxpy@gmail.com>
License: MIT License
Project-URL: Repository, https://github.com/lnxpy/pyaction
Classifier: Development Status :: 5 - Production/Stable
Classifier: Intended Audience :: Developers
Classifier: License :: OSI Approved :: MIT License
Classifier: Operating System :: OS Independent
Classifier: Programming Language :: Python
Classifier: Programming Language :: Python :: 3.8
Classifier: Programming Language :: Python :: 3.9
Classifier: Programming Language :: Python :: 3.10
Classifier: Programming Language :: Python :: 3.11
Classifier: Programming Language :: Python :: 3.12
Classifier: Programming Language :: Python :: 3 :: Only
Requires-Python: >=3.8
License-File: LICENSE
Requires-Dist: spacy >=3.7.5
Provides-Extra: dev
Requires-Dist: coverage ; extra == 'dev'
Requires-Dist: pytest-cookies ; extra == 'dev'
